MANIFEST.in
setup.py
nsi/__init__.py
nsi.metadataextractor.egg-info/PKG-INFO
nsi.metadataextractor.egg-info/SOURCES.txt
nsi.metadataextractor.egg-info/dependency_links.txt
nsi.metadataextractor.egg-info/entry_points.txt
nsi.metadataextractor.egg-info/not-zip-safe
nsi.metadataextractor.egg-info/requires.txt
nsi.metadataextractor.egg-info/top_level.txt
nsi/metadataextractor/__init__.py
nsi/metadataextractor/cmdline.py
nsi/metadataextractor/preparator.py
nsi/metadataextractor/xml_parser.py
nsi/metadataextractor/corpus/campus.txt
nsi/metadataextractor/corpus/institution.txt
nsi/metadataextractor/corpus/names.txt
nsi/metadataextractor/extractors/__init__.py
nsi/metadataextractor/extractors/event.py
nsi/metadataextractor/extractors/periodic.py
nsi/metadataextractor/extractors/tcc.py
nsi/metadataextractor/templates/event.xml
nsi/metadataextractor/templates/periodic.xml
nsi/metadataextractor/templates/tcc.xml
nsi/metadataextractor/tests/__init__.py
nsi/metadataextractor/tests/testExtractor.py
nsi/metadataextractor/tests/testParser.py