Metadata-Version: 1.0
Name: nsi.metadataextractor
Version: 1.2
Summary: A template-based metadata extractor.
Home-page: UNKNOWN
Author: Oswaldo Ferreira
Author-email: oswluizf@gmail.com
License: UNKNOWN
Keywords: metadata extraction python
Platform: UNKNOWN
